wexample_config-0.0.97.dist-info/METADATA
wexample_config-0.0.97.dist-info/WHEEL
wexample_config-0.0.97.dist-info/entry_points.txt
wexample_config/__init__.py
wexample_config/__pycache__/__init__.py
wexample_config/classes/__init__.py
wexample_config/classes/__pycache__/__init__.py
wexample_config/classes/abstract_config_manager.py
wexample_config/config_option/__init__.py
wexample_config/config_option/__pycache__/__init__.py
wexample_config/config_option/abstract_config_option.py
wexample_config/config_option/abstract_list_config_option.py
wexample_config/config_option/abstract_nested_config_option.py
wexample_config/config_option/children_config_option.py
wexample_config/config_option/config_option.py
wexample_config/config_option/name_config_option.py
wexample_config/config_value/__init__.py
wexample_config/config_value/__pycache__/__init__.py
wexample_config/config_value/callback_render_config_value.py
wexample_config/config_value/config_value.py
wexample_config/config_value/config_value_collection.py
wexample_config/config_value/custom_type_config_value.py
wexample_config/config_value/nested_config_value.py
wexample_config/const/__init__.py
wexample_config/const/__pycache__/__init__.py
wexample_config/const/types.py
wexample_config/demo/__init__.py
wexample_config/demo/__pycache__/__init__.py
wexample_config/demo/config_option/__init__.py
wexample_config/demo/config_option/demo_custom_value_config_option.py
wexample_config/demo/config_option/demo_dict_config_option.py
wexample_config/demo/config_option/demo_dict_extensible_option.py
wexample_config/demo/config_option/demo_extensible_config_option.py
wexample_config/demo/config_option/demo_list_config_option.py
wexample_config/demo/config_option/demo_nested_config_option.py
wexample_config/demo/config_option/demo_union_config_option.py
wexample_config/demo/demo_config_manager.py
wexample_config/demo/option_provider/__init__.py
wexample_config/demo/option_provider/demo_options_provider.py
wexample_config/exception/__init__.py
wexample_config/exception/__pycache__/__init__.py
wexample_config/exception/invalid_option_exception.py
wexample_config-0.0.97.dist-info/RECORD
